translator/consts.py
translator/exceptions.py
translator/translator.py
translator/utils.py
translator_cli-0.5.23.dist-info/METADATA
translator_cli-0.5.23.dist-info/WHEEL
translator_cli-0.5.23.dist-info/licenses/LICENSE
translator_cli-0.5.23.dist-info/RECORD
