Metadata-Version: 2.4
Name: translator-cli
Version: 0.5.23
Summary: A tool for translating texts between different languages
Author-email: Sergio Puche García <serpucga@inf.upv.es>
License-File: LICENSE
Requires-Python: ~=3.12
Requires-Dist: boto3==1.28.52
Requires-Dist: botocore==1.31.52
Requires-Dist: chatgpt-klient==0.8.0
Requires-Dist: deep-translator==1.11.4
Requires-Dist: deepl==1.15.0
Requires-Dist: loguru<0.7,>=0.6.0
Requires-Dist: logutils-serpucga==0.2.1
Requires-Dist: multiprocess<0.71,>=0.70.13
Requires-Dist: openai==1.10.0
Requires-Dist: requests<3,>=2.28.1
Requires-Dist: translators==5.8.3
